greatpy/__init__.py
greatpy/pl/__init__.py
greatpy/pl/basic.py
greatpy/tl/__init__.py
greatpy/tl/great.py
greatpy/tl/regdom.py
greatpy/tl/utils.py
greatpy/tl/utils_r.py
greatpy-0.0.1.dist-info/LICENSE
greatpy-0.0.1.dist-info/WHEEL
greatpy-0.0.1.dist-info/METADATA
greatpy-0.0.1.dist-info/RECORD
