Metadata-Version: 2.1
Name: greatpy
Version: 0.0.1
Summary: Implementation of GREAT in Python
Author: Ignacio Ibarra, Tom Mauger-Birocheau
Maintainer-email: Ignacio Ibarra <ignacio.ibarra@helmholtz-muenchen.de>, Tom Mauger-Birocheau <tom.mauger-birocheau@etu.univ-cotedazur.fr>
Requires-Python: >=3.8
Requires-Dist: statsmodels
Requires-Dist: seaborn
Requires-Dist: dask
Requires-Dist: scipy
Requires-Dist: gprofiler
Requires-Dist: bump2version ; extra == "dev"
Requires-Dist: sphinx>=4 ; extra == "doc"
Requires-Dist: furo ; extra == "doc"
Requires-Dist: myst-parser ; extra == "doc"
Requires-Dist: sphinxcontrib-bibtex>=1.0.0 ; extra == "doc"
Requires-Dist: scanpydoc[typehints]>=0.7.4 ; extra == "doc"
Requires-Dist: nbsphinx ; extra == "doc"
Requires-Dist: ipython>=8.3.0 ; extra == "doc"
Requires-Dist: pytest ; extra == "test"
Requires-Dist: pytest-cov ; extra == "test"
Project-URL: Documentation, https://greatpy.readthedocs.io/
Project-URL: Home-page, https://github.com/theislab/greatpy
Project-URL: Source, https://github.com/theislab/greatpy
Provides-Extra: dev
Provides-Extra: doc
Provides-Extra: test
